{
  "type": "FeatureCollection",
  "features": [
    {
      "type": "Feature",
      "properties": {
        "name": "Station 1",
        "description": "Water quality monitoring station"
      },
      "geometry": {
        "type": "Point",
        "coordinates": [-122.4194, 37.7749]
      }
    }
  ]
}

